bisos/__init__.py
bisos/graphviz/__init__.py
bisos/graphviz/graphvizSeed.py
bisos/graphviz/graphviz_csu.py
bisos.graphviz-0.19.data/scripts/exmpl-graphviz.cs
bisos.graphviz-0.19.data/scripts/seedGraphviz.cs
bisos.graphviz-0.19.dist-info/METADATA
bisos.graphviz-0.19.dist-info/WHEEL
bisos.graphviz-0.19.dist-info/top_level.txt
bisos.graphviz-0.19.dist-info/RECORD
